IA22001UNO/__init__.py
IA22001UNO/metodos.py
ia22001uno-0.1.0.dist-info/METADATA
ia22001uno-0.1.0.dist-info/WHEEL
ia22001uno-0.1.0.dist-info/top_level.txt
ia22001uno-0.1.0.dist-info/RECORD
