Metadata-Version: 2.4
Name: IA22001UNO
Version: 0.1.0
Summary: Creación de una librería para resolver sistemas de ecuaciones lineales y ecuaciones no lineales
Home-page: https://github.com/ia22001MichelleIglesias/IA22001UNO
Author: Michelle Iglesias
Author-email: ia22001@ues.edu.sv
Classifier: Programming Language :: Python :: 3
Classifier: License :: OSI Approved :: MIT License
Classifier: Operating System :: OS Independent
Requires-Python: >=3.6
Requires-Dist: numpy
Dynamic: author
Dynamic: author-email
Dynamic: classifier
Dynamic: description
Dynamic: description-content-type
Dynamic: home-page
Dynamic: requires-dist
Dynamic: requires-python
Dynamic: summary
